COPYRIGHT
MANIFEST.in
Makefile
README
setup.cfg
setup.py
test/__init__.py
test/__init__.pyc
test/test_def_list.py
test/test_extensions.py
test/test_fenced_code.py
test/test_footnotes.py
test/test_freelinks.py
test/test_safe_html.py
test/test_spacelinks.py
test/test_transclusion.py
test/test_urlification.py
test/test_wikilinks.py
test/__pycache__/test_def_list.cpython-27-PYTEST.pyc
test/__pycache__/test_extensions.cpython-27-PYTEST.pyc
test/__pycache__/test_fenced_code.cpython-27-PYTEST.pyc
test/__pycache__/test_footnotes.cpython-27-PYTEST.pyc
test/__pycache__/test_freelinks.cpython-27-PYTEST.pyc
test/__pycache__/test_safe_html.cpython-27-PYTEST.pyc
test/__pycache__/test_spacelinks.cpython-27-PYTEST.pyc
test/__pycache__/test_transclusion.cpython-27-PYTEST.pyc
test/__pycache__/test_urlification.cpython-27-PYTEST.pyc
test/__pycache__/test_wikilinks.cpython-27-PYTEST.pyc
tiddlywebplugins/__init__.py
tiddlywebplugins.markdown.egg-info/PKG-INFO
tiddlywebplugins.markdown.egg-info/SOURCES.txt
tiddlywebplugins.markdown.egg-info/dependency_links.txt
tiddlywebplugins.markdown.egg-info/namespace_packages.txt
tiddlywebplugins.markdown.egg-info/not-zip-safe
tiddlywebplugins.markdown.egg-info/pbr.json
tiddlywebplugins.markdown.egg-info/requires.txt
tiddlywebplugins.markdown.egg-info/top_level.txt
tiddlywebplugins/markdown/__init__.py
tiddlywebplugins/markdown/autolink.py
tiddlywebplugins/markdown/links.py
tiddlywebplugins/markdown/render.py
tiddlywebplugins/markdown/transclusion.py