Metadata-Version: 1.0
Name: tiddlywebplugins.markdown
Version: 1.3.0
Summary: Markdown rendering for TiddlyWeb
Home-page: http://pypi.python.org/pypi/tiddlywebplugins.markdown
Author: Chris Dent
Author-email: cdent@peermore.com
License: UNKNOWN
Platform: Posix; MacOS X; Windows
